{
  "rooms": [
    {
      "name": "bathroom",
      "spawns" : [
        {
          "x": 0,
          "y": 0
        },
        {
          "x": 0,
          "y": 0
        }
      ]
    },
    {
      "name": "livingRoom",
      "spawns": [

      ]
    },
    {
      "name": "kitchen",
      "spawns": [

      ]
    },
    {
      "name": "bedroom",
      "spawns": [
        {
          "x": 816,
          "y": 943
        }
      ]
    },
    {
      "name": "garden",
      "spawns": [
        {
          "x": 944,
          "y": 355
        },
        {
          "x": 730,
          "y": 404
        },
        {
          "x": 1052,
          "y": 391
        },
        {
          "x": 1031,
          "y": 279
        },
        {
          "x": 742,
          "y": 448
        }
      ]
    }
  ]
}
